bioarch/__init__.py
bioarch/age.py
bioarch/age_test.py
bioarch/context.py
bioarch/context_test.py
bioarch/individual.py
bioarch/individual_test.py
bioarch/joints.py
bioarch/joints_test.py
bioarch/left_right.py
bioarch/left_right_test.py
bioarch/mouth.py
bioarch/mouth_test.py
bioarch/occupational_markers.py
bioarch/occupational_markers_test.py
bioarch/sex.py
bioarch/sex_test.py
bioarch/trauma.py
bioarch/trauma_test.py
bioarch/test/__init__.py
bioarch-0.0.34.dist-info/LICENSE
bioarch-0.0.34.dist-info/METADATA
bioarch-0.0.34.dist-info/WHEEL
bioarch-0.0.34.dist-info/top_level.txt
bioarch-0.0.34.dist-info/RECORD
