Metadata-Version: 2.1
Name: bioarch
Version: 0.0.34
Summary: Python bioarchaeology
Home-page: https://github.com/TheBiggerGuy/bioarch
Author: Guy Taylor
Author-email: thebigguy.co.uk@gmail.com
License: MIT
Platform: UNKNOWN
Classifier: Development Status :: 3 - Alpha
Classifier: Programming Language :: Python
Classifier: Programming Language :: Python :: 3
Classifier: Programming Language :: Python :: 3.7
Classifier: Programming Language :: Python :: 3 :: Only
Classifier: Programming Language :: Python :: Implementation :: CPython
Classifier: License :: OSI Approved :: MIT License
Requires-Python: >=3.7
